pycvesearch/__init__.py
pycvesearch/core.py
pycvesearch/py.typed
pycvesearch-1.1.dist-info/COPYING
pycvesearch-1.1.dist-info/WHEEL
pycvesearch-1.1.dist-info/METADATA
pycvesearch-1.1.dist-info/RECORD
