Metadata-Version: 2.1
Name: pycvesearch
Version: 1.1
Summary: Python API for CVE search.
Home-page: https://github.com/cve-search/PyCVESearch
License: Apache-2.0
Author: Raphaël Vinot
Author-email: raphael.vinot@circl.lu
Requires-Python: >=3.7,<4.0
Classifier: Development Status :: 5 - Production/Stable
Classifier: Environment :: Console
Classifier: Intended Audience :: Science/Research
Classifier: Intended Audience :: Telecommunications Industry
Classifier: License :: OSI Approved :: Apache Software License
Classifier: Programming Language :: Python :: 3
Classifier: Programming Language :: Python :: 3.10
Classifier: Programming Language :: Python :: 3.7
Classifier: Programming Language :: Python :: 3.8
Classifier: Programming Language :: Python :: 3.9
Classifier: Topic :: Internet
Classifier: Topic :: Security
Requires-Dist: requests (>=2.27.1,<3.0.0)
Project-URL: Repository, https://github.com/cve-search/PyCVESearch
